sapiens_machine/__init__.py
sapiens_machine/__main__.py
sapiens_machine/cextension.py
sapiens_machine/download_libraries.py
sapiens_machine/functional.py
sapiens_machine/utils.py
sapiens_machine/autograd/__init__.py
sapiens_machine/autograd/_functions.py
sapiens_machine/cuda_setup/__init__.py
sapiens_machine/cuda_setup/env_vars.py
sapiens_machine/cuda_setup/main.py
sapiens_machine/nn/__init__.py
sapiens_machine/nn/modules.py
sapiens_machine/nn/triton_based_modules.py
sapiens_machine/optim/__init__.py
sapiens_machine/optim/adagrad.py
sapiens_machine/optim/adam.py
sapiens_machine/optim/adamw.py
sapiens_machine/optim/lamb.py
sapiens_machine/optim/lars.py
sapiens_machine/optim/lion.py
sapiens_machine/optim/optimizer.py
sapiens_machine/optim/rmsprop.py
sapiens_machine/optim/sgd.py
sapiens_machine/research/__init__.py
sapiens_machine/research/autograd/__init__.py
sapiens_machine/research/autograd/_functions.py
sapiens_machine/research/nn/__init__.py
sapiens_machine/research/nn/modules.py
sapiens_machine/triton/__init__.py
sapiens_machine/triton/dequantize_rowwise.py
sapiens_machine/triton/int8_matmul_mixed_dequantize.py
sapiens_machine/triton/int8_matmul_rowwise_dequantize.py
sapiens_machine/triton/quantize_columnwise_and_transpose.py
sapiens_machine/triton/quantize_global.py
sapiens_machine/triton/quantize_rowwise.py
sapiens_machine/triton/triton_utils.py
sapiens_machine-1.1.0.dist-info/LICENSE.txt
sapiens_machine-1.1.0.dist-info/METADATA
sapiens_machine-1.1.0.dist-info/WHEEL
sapiens_machine-1.1.0.dist-info/top_level.txt
sapiens_machine-1.1.0.dist-info/RECORD
