Metadata-Version: 2.2
Name: sapiens_machine
Version: 1.1.0
Home-page: https://github.com/sapiens-technology/sapiens_machine
Author: OPENSAPI
License: Proprietary Software
License-File: LICENSE.txt
Requires-Dist: scipy
Requires-Dist: requests
Dynamic: author
Dynamic: home-page
Dynamic: license
Dynamic: requires-dist
